Projects/project3/cache_2b/cache_2b.srcs/sources_1/new/cache2b.v
`timescale 1ns / 1ps
module cache2b(
    // this part is to accomplish write back in 2-way associative mode
    output reg  [7:0]   cacheData,	// we read the data from the cache   
	input               write,		// read: 0 write: 1
	input       [9:0]   address,	// address get from CPU
	input       [7:0]   CPUwrite,	// Data going to write in the cache
    output reg  [9:0]   memoryAddress,  // the output address to main memory
    output reg          memWrite,     // to tell the CPU to write or read  
    output reg  [127:0] writeCacheData, // output of cache of 4 words going to write into the main memory
    input       [127:0] readMain,  // data read from the memory
    output reg          detectHit      // hit or miss, hit for 1
    );

// here we initialized the cache with all zero
// altogether 270 bits:  
// first block: 267 valid bit, 266-262 5_bit tag, 261-134 128_bit data
// second block: 133 valid bit, 132-128 5_bit tag, 127-0 128_bit data
// two dirty bits. 269 for first block, 268 for the second block
    reg block;
    reg LRUblock[1:0];  //which block is LRU
    reg [269:0] cache [1:0];  //one set
	initial begin
		cache[0] = 270'b0;cache[1] = 270'b0;
		block = 1'b0; memoryAddress = 10'b0;
		LRUblock[1] = 1'b0;
		LRUblock[0] = 1'b0;
        memWrite = 1'b0;
	end
    wire hit; wire [3:0] byte_addr;		// the address to select the address

 assign byte_addr = address[3:0];
    assign hit = ((cache[0][267] == 1'b1 && cache[0][266:262] == address[9:5] ) || (cache[1][267] == 1'b1 && cache[1][266:262] == address[9:5]) || (cache[0][133] == 1'b1 && cache[0][132:128] == address[9:5])|| (cache[1][133] == 1'b1 && cache[1][132:128] == address[9:5]))? 1:0;

    always@(address or write or CPUwrite) begin
        
        detectHit = ((cache[0][267] == 1'b1 && cache[0][266:262] == address[9:5] ) || (cache[1][267] == 1'b1 && cache[1][266:262] == address[9:5]) || (cache[0][133] == 1'b1 && cache[0][132:128] == address[9:5])|| (cache[1][133] == 1'b1 && cache[1][132:128] == address[9:5]))? 1:0;

    end
    always@(*) begin
          begin
                memoryAddress = address;
                if(write == 1'b0) begin //if we have read instruction 
                    memWrite = 1'b0;
                    if(hit == 1'b1) begin //if hit return data to CPU
                        if (address[4] == 0) block = 0;else block = 1; // which set does it cover
                        if (cache[block][132:128] == address[9:5]) LRUblock[block] = 1'b1; else LRUblock[block] = 1'b0; // which is LRU block in the corresponding set
                        if (LRUblock[block] == 1'b1) begin
                            case (byte_addr)
					        0: cacheData <= cache[block][127:120]; 1: cacheData <= cache[block][119:112];
					        2: cacheData <= cache[block][111:104];3: cacheData <= cache[block][103:96];
					        4: cacheData <= cache[block][95:88];5: cacheData <= cache[block][87:80];
					        6: cacheData <= cache[block][79:72];7: cacheData <= cache[block][71:64];
					        8: cacheData <= cache[block][63:56];9: cacheData <= cache[block][55:48];
					        10: cacheData <= cache[block][47:40];11: cacheData <= cache[block][39:32];
					        12: cacheData <= cache[block][31:24];13: cacheData <= cache[block][23:16];
					        14: cacheData <= cache[block][15:8];15: cacheData <= cache[block][7:0];
					        default: ;
				            endcase
				        end
				        else begin
				            case (byte_addr)
					        0: cacheData <= cache[block][261:254]; 1: cacheData <= cache[block][253:246];
					        2: cacheData <= cache[block][245:238];3: cacheData <= cache[block][237:230];
					        4: cacheData <= cache[block][229:222];5: cacheData <= cache[block][221:214];
					        6: cacheData <= cache[block][213:206];7: cacheData <= cache[block][205:198];
					        8: cacheData <= cache[block][197:190];9: cacheData <= cache[block][189:182];
					        10: cacheData <= cache[block][181:174];11: cacheData <= cache[block][173:166];
					        12: cacheData <= cache[block][165:158];13: cacheData <= cache[block][157:150];
					        14: cacheData <= cache[block][149:142];15: cacheData <= cache[block][141:134];
					        default: ;
					        endcase
				        end
                    end
                    else begin //if not hit or some unknown instructions
                        if (address[4] == 0) block = 0;else block = 1; // use to judge the set

                        #0.1;
                       
                       if (LRUblock[block] == 1'b0) begin
                       if (cache[block][268]==1'b1) begin 
                            #0.1;
                            memWrite = 1'b1;
                            memoryAddress [9:5] = cache[block][132:128];
                            memoryAddress [4] = block;
                            memoryAddress [3:0] = 4'b0;
                            writeCacheData<= cache[block][127:0]; // if dirty, write back to the main memory
                            cache[block][268] = 1'b0;
                       #0.1;
                            memWrite = 1'b0;
                            memoryAddress = address;
                       end
                       #0.1;
                        cache[block][127:0] = readMain; // get new block of data
                        #0.1
                        case (byte_addr)
					        0: cacheData = cache[block][127:120];1: cacheData = cache[block][119:112];
					        2: cacheData = cache[block][111:104];3: cacheData = cache[block][103:96];
					        4: cacheData = cache[block][95:88];5: cacheData = cache[block][87:80];
					        6: cacheData = cache[block][79:72];7: cacheData = cache[block][71:64];
					        8: cacheData = cache[block][63:56];9: cacheData = cache[block][55:48];
					        10: cacheData = cache[block][47:40];11: cacheData = cache[block][39:32];
					        12: cacheData = cache[block][31:24];13: cacheData = cache[block][23:16];
					        14: cacheData = cache[block][15:8];15: cacheData = cache[block][7:0]; 
					        default: ;
				        endcase
                        cache[block][133] <= 1'b1;   // set valid = 1
                        cache[block][132:128]<=address[9:5]; // change tag to the target address
                        cache[block][268] <= 1'b0;  // not dirty
                        LRUblock[block] <= 1'b1;    //set new LRU block
                        end
                        else begin
                        if (cache[block][269]==1'b1) begin 
                            #0.1;
                            memWrite = 1'b1;
                            memoryAddress [9:5] = cache[block][266:262];
                            memoryAddress [4] = block;
                            memoryAddress [3:0] = 4'b0;
                            writeCacheData<= cache[block][261:134]; // if dirty, write back to the main memory
                            cache[block][269] = 1'b0;
                       #0.1;
                            memWrite = 1'b0;
                            memoryAddress = address;
                       end

                        #0.1;                       
                        cache[block][261:134] = readMain; // get new block of data
                        #0.1
                        case (byte_addr)
					        0: cacheData = cache[block][261:254]; 1: cacheData = cache[block][253:246];
					        2: cacheData = cache[block][245:238];3: cacheData = cache[block][237:230];
					        4: cacheData = cache[block][229:222];5: cacheData = cache[block][221:214];
					        6: cacheData = cache[block][213:206];7: cacheData = cache[block][205:198];
					        8: cacheData = cache[block][197:190];9: cacheData = cache[block][189:182];
					        10: cacheData = cache[block][181:174];11: cacheData = cache[block][173:166];
					        12: cacheData = cache[block][165:158];13: cacheData = cache[block][157:150];
					        14: cacheData = cache[block][149:142];15: cacheData = cache[block][141:134]; 
					        default: ;
				        endcase
                        cache[block][267] <= 1'b1;   // set valid = 1
                        cache[block][266:262]<=address[9:5]; // change tag to the target address
                        LRUblock[block] <= 1'b0;// set new LRU block
                        cache[block][269] <= 1'b0;  // not dirty
                        end
                    end
                end
                else if (write == 1'b1) begin // if we have write instruction
                    cacheData <= 8'b0;
                    memWrite = 1'b0;
                    if(hit == 1'b1) begin // if hit write to cache
                        if (address[4] == 0) block = 0; else block = 1;// which set
                        
                        if (cache[block][132:128] == address[9:5]) LRUblock[block] = 1'b1; else LRUblock[block] = 1'b0;// which is the least recently used block
                        if (LRUblock[block] == 1'b1) begin 
                        case (byte_addr) // here we write the CPU data to the cache
					        0: cache[block][127:120] <= CPUwrite;1: cache[block][119:112] <= CPUwrite;
					        2: cache[block][111:104] <= CPUwrite;3: cache[block][103:96] <= CPUwrite;
					        4: cache[block][95:88] <= CPUwrite;5: cache[block][87:80] <= CPUwrite;
					        6: cache[block][79:72] <= CPUwrite;7: cache[block][71:64] <= CPUwrite;
					        8: cache[block][63:56] <= CPUwrite;9: cache[block][55:48] <= CPUwrite;
					        10: cache[block][47:40] <= CPUwrite;11: cache[block][39:32] <= CPUwrite;
					        12: cache[block][31:24] <= CPUwrite;13: cache[block][23:16] <= CPUwrite;
					        14: cache[block][15:8] <= CPUwrite;15: cache[block][7:0] <= CPUwrite;
					        default: ;
				        endcase
				        cache[block][268]<=1'b1; //dirty
				        //cache[block][133]<=1'b1; //valid
				        end 
				        else begin
				        case (byte_addr)
					        0: cache[block][261:254] <= CPUwrite; 1: cache[block][253:246] <= CPUwrite;
					        2: cache[block][245:238] <= CPUwrite;3: cache[block][237:230] <= CPUwrite;
					        4: cache[block][229:222] <= CPUwrite;5: cache[block][221:214] <= CPUwrite;
					        6: cache[block][213:206] <= CPUwrite;7: cache[block][205:198] <= CPUwrite;
					        8: cache[block][197:190] <= CPUwrite;9: cache[block][189:182] <= CPUwrite;
					        10: cache[block][181:174] <= CPUwrite;11: cache[block][173:166] <= CPUwrite;
					        12: cache[block][165:158] <= CPUwrite;13: cache[block][157:150] <= CPUwrite;
					        14: cache[block][149:142] <= CPUwrite;15: cache[block][141:134] <= CPUwrite; 
					        default: ;
				        endcase
				        cache[block][269]<=1'b1; //dirty
				        //cache[block][267]<=1'b1; //valid
				        end
                                                                                            
                    end
                    else begin	// if no hit or other instructions
                        if (address[4] == 0) block = 0; else block = 1;// which set                                    
                        #0.1;
                        if (LRUblock[block] == 1'b0) begin                        
                        if (cache[block][268]==1'b1) begin 
                            #0.1;
                            memWrite = 1'b1;
                            memoryAddress [9:5] = cache[block][132:128];
                            memoryAddress [4] = block;
                            memoryAddress [3:0] = 4'b0;
                            writeCacheData<= cache[block][127:0]; // if dirty, write back to the main memory
                            cache[block][268] = 1'b0;
                       #0.1;
                            memWrite = 1'b0;
                            memoryAddress = address;
                       end
                        #0.1;
                            cache[block][127:0] = readMain; // load from main memory to cache
                        #0.1
                        cache[block][133] = 1'b1;    // set valid = 1
                        cache[block][132:128] = address[9:5]; // change tag size to target address
                        cache[block][268]<=1'b1;//dirty
                        // write data
                        case (byte_addr)
					        0: cache[block][127:120] = CPUwrite;1: cache[block][119:112] = CPUwrite;
					        2: cache[block][111:104] = CPUwrite;3: cache[block][103:96] = CPUwrite;
					   		4: cache[block][95:88] = CPUwrite;5: cache[block][87:80] = CPUwrite;
					        6: cache[block][79:72] = CPUwrite;7: cache[block][71:64] = CPUwrite;
					        8: cache[block][63:56] = CPUwrite;9: cache[block][55:48] = CPUwrite;
					        10: cache[block][47:40] = CPUwrite;11: cache[block][39:32] = CPUwrite;		        
					        12: cache[block][31:24] = CPUwrite;13: cache[block][23:16] = CPUwrite;
					        14: cache[block][15:8] = CPUwrite;15: cache[block][7:0] = CPUwrite;
					        default: ;
				        endcase
                        #0.1
                           memWrite = 1'b1;
                           memoryAddress [9:4] = address[9:4];
                           memoryAddress [3:0] = 4'b0;
//                           writeCacheData = cache[block][127:0]; // load the whole block into memory
                        end
				        else begin
				        if (cache[block][269]==1'b1) begin 
                            #0.1;
                            memWrite = 1'b1;
                            memoryAddress [9:5] = cache[block][266:262];
                            memoryAddress [4] = block;
                            memoryAddress [3:0] = 4'b0;
                            writeCacheData<= cache[block][261:134]; // if dirty, write back to the main memory
                            cache[block][269] = 1'b0;
                       #0.1;
                            memWrite = 1'b0;
                            memoryAddress = address;
                       end				        				        				       
                        #0.1;
				        cache[block][261:134] = readMain; // load from main memory to cache
                        #0.1
                        cache[block][267] = 1'b1;    // set valid = 1
                        cache[block][266:262] = address[9:5]; // change tag size to target address
                        cache[block][269] = 1'b1; //dirty
                        // write data
				        case (byte_addr)
					        0: cache[block][261:254] <= CPUwrite; 1: cache[block][253:246] <= CPUwrite;
					        2: cache[block][245:238] <= CPUwrite;3: cache[block][237:230] <= CPUwrite;
					        4: cache[block][229:222] <= CPUwrite;5: cache[block][221:214] <= CPUwrite;
					        6: cache[block][213:206] <= CPUwrite;7: cache[block][205:198] <= CPUwrite;
					        8: cache[block][197:190] <= CPUwrite;9: cache[block][189:182] <= CPUwrite;
					        10: cache[block][181:174] <= CPUwrite;11: cache[block][173:166] <= CPUwrite;
					        12: cache[block][165:158] <= CPUwrite;13: cache[block][157:150] <= CPUwrite;
					        14: cache[block][149:142] <= CPUwrite;15: cache[block][141:134] <= CPUwrite; 
					        default: ;
				        endcase

                        #0.1
                           memWrite = 1'b1;
                           memoryAddress [9:4] = address[9:4];
                           memoryAddress [3:0] = 4'b0;
  //                         writeCacheData = cache[block][266:262]; // load the whole block into memory 
				        end                                                                                 
                        #0.1
                           memWrite = 1'b0;
                           memoryAddress = address;                           
                end
            end
        end
    end
    

endmodule

Projects/project3/cache_2b/cache_2b.srcs/sources_1/new/main_memory.v
`timescale 1ns / 1ps
module main_memory (
    input       write,
    input       [9:0]  FullAddress,
    input       [127:0]  WriteData,
    output      [127:0]  ReadData
);
    integer i;
    wire    [7:0]  Address;
    assign Address[7:2] = FullAddress[9:4];
    assign Address[1:0] = 2'b0;  // we need to get the effective address
    // initialize memory
    // the size of mainmemory is 256
    reg [31:0] Mainmemory [0:255];
    // set all memory to zero
    initial begin
        for (i = 0; i < 256; i = i + 1)
            Mainmemory[i] = 32'b0;
    end
    // use random numbers to generate the memory 
    //initial begin   
     //for (i = 0; i < 256; i = i + 1)
    //Mainmemory[i]={$random};  
     // end    
        assign ReadData = {Mainmemory[Address] , Mainmemory[Address+1] , Mainmemory[Address+2] , Mainmemory[Address+3]};                           
    always @* begin
    // when we have write, we can replace the original main memory data with new ones
       if (write == 1) begin
       Mainmemory[Address] = WriteData[127:96]; Mainmemory[Address+1] = WriteData[95:64];
       Mainmemory[Address+2] = WriteData[63:32];Mainmemory[Address+3] = WriteData[31:0];
       end
    end
endmodule

Projects/project3/cache_2b/cache_2b.srcs/sources_1/new/combined.v
`timescale 1ns / 1ps
`include "main_memory.v"
`include "cache2b.v"
module combined(
    output [7:0] cacheData,	// data read from cache
	output hit,			// 0 for miss, 1 for hit
	input write,		// write/read from CPU, 0 for read 1 for write
	input [9:0] address,	// address received from CPU
	input [7:0] CPUwrite	// data received from CPU
    );
    wire memwrite;
    wire [127:0] readMain;	// we need to read data from main memory if not hit
    wire [127:0] writeCacheData;	// data write to memory
    wire [9:0] memoryAddress;
    
    main_memory MainMemory(memWrite, memoryAddress, writeCacheData, readMain);
 // this part is designed to eliminate the delay
    cache2b combined_module(
        .cacheData(cacheData),		
	    .write(write),		// write/read from CPU, 0 for read 1 for write
	    .address(address),	// address received from CPU
	    .CPUwrite(CPUwrite),	// data received from CPU
        .writeCacheData(writeCacheData), // output data from the cache to the memory
        .readMain(readMain),  //  data read from the memory
        .detectHit(hit),// whether hit or not
        .memoryAddress(memoryAddress), // the output address to main memory
        .memWrite(memWrite) // to tell the CPU to write or not
    );

endmodule

Projects/project3/cache_2b/cache_2b.srcs/sim_1/new/cache2b_test.v
//`include "combined.v"
module cache_2b_test();
    reg read_write;
    reg [9:0] address;
    reg [7:0] write_data;
    wire [7:0] read_data;
    wire hit;
    integer count = 0;// here we use this to control the display

    
    initial 
    begin
    #0  $dumpfile("testbench.vcd");
        $dumpvars(0, cache_2b_test);
    #100 $finish;
    end
    
    
    initial 
    begin
        #0 read_write = 0; address = 10'b0000000000; //should miss
        #10 read_write = 1; address = 10'b0000000000; write_data = 8'b11111111; //should hit
        #10 read_write = 0; address = 10'b0000000000; //should hit and read out 0xff
    //	
    //	//here check main memory content, 
    //	//the first byte should remain 0x00 if it is write-back, 
    //	//should change to 0xff if it is write-through.
    //	
        #10 read_write = 0; address = 10'b1000000000; //should miss
        #10 read_write = 0; address = 10'b0000000000; //should hit for 2-way associative, should miss for directly mapped
        
        #10 read_write = 0; address = 10'b1100000000; //should miss
        #10 read_write = 0; address = 10'b1000000000; //should miss both for directly mapped and for 2-way associative (Least-Recently-Used policy)
    //	//here check main memory content, 
    //	//the first byte should be 0xff
    end
    
    combined cache(read_data, hit, read_write, address, write_data);
    
    always #5 begin
            $display("count=%d read_write = %b",count, read_write);
            $display("count=%d ReadData = 0x%H",count, cache.cacheData);
            $display("count=%d MainMemory = 0x%H",count,cache.MainMemory.Mainmemory[0]);
            $display("----------------------------------------------------------");
            count=count+1;
        end
endmodule

Projects/project3/cache_2b/cache_2b.sim/sim_1/behav/xsim/testbench.vcd
$date
   Thu Nov 26 09:58:47 2020
$end
$version
  2020.1
$end
$timescale
  1ps
$end
$scope module cache_2b_test $end
$var reg 1 ! read_write $end
$var reg 10 " address [9:0] $end
$var reg 8 # write_data [7:0] $end
$var wire 8 $ read_data [7:0] $end
$var wire 1 % hit $end
$var integer 32 & count $end
$scope module cache $end
$var wire 8 $ cacheData [7:0] $end
$var wire 1 % hit $end
$var wire 1 ' write $end
$var wire 10 ( address [9:0] $end
$var wire 8 ) CPUwrite [7:0] $end
$var wire 1 * memwrite $end
$var wire 128 + readMain [127:0] $end
$var wire 128 , writeCacheData [127:0] $end
$var wire 10 - memoryAddress [9:0] $end
$var wire 1 . memWrite $end
$scope module MainMemory $end
$var wire 1 . write $end
$var wire 10 - FullAddress [9:0] $end
$var wire 128 , WriteData [127:0] $end
$var wire 128 + ReadData [127:0] $end
$var integer 32 / i $end
$var wire 8 0 Address [7:0] $end
$upscope $end
$scope module combined_module $end
$var reg 8 1 cacheData [7:0] $end
$var wire 1 ' write $end
$var wire 10 ( address [9:0] $end
$var wire 8 ) CPUwrite [7:0] $end
$var reg 10 2 memoryAddress [9:0] $end
$var reg 1 3 memWrite $end
$var reg 128 4 writeCacheData [127:0] $end
$var wire 128 + readMain [127:0] $end
$var reg 1 5 detectHit $end
$var reg 1 6 block $end
$var wire 1 7 hit $end
$var wire 4 8 byte_addr [3:0] $end
$upscope $end
$upscope $end
$upscope $end
$enddefinitions $end
#0
$dumpvars
0!
b0 "
bx #
bx $
0%
b0 &
0'
b0 (
bx )
z*
b0 +
bx ,
b0 -
0.
b100000000 /
b0 0
bx 1
b0 2
03
bx 4
05
06
07
b0 8
$end
#300
b0 $
b0 1
b0 2
03
17
#5000
b1 &
#10000
1!
b0 "
b11111111 #
1%
b10 &
1'
b11111111 )
b0 1
b0 2
03
15
#15000
b11 &
#20000
0!
b0 "
b11111111 $
b100 &
0'
b11111111 1
b0 2
03
15
#25000
b101 &
#30000
b1000000000 "
0%
b110 &
b1000000000 (
b0 +
b1000000000 -
b10000000 0
b1000000000 2
03
05
07
#30300
b0 $
b0 1
b1000000000 2
03
17
#35000
b111 &
#40000
b0 "
b11111111 $
1%
b1000 &
b0 (
b0 +
b0 -
b0 0
b11111111 1
b0 2
03
15
17
#45000
b1001 &
#50000
b1100000000 "
0%
b1010 &
b1100000000 (
b0 +
b1100000000 -
b11000000 0
b1100000000 2
03
05
07
#50300
b0 $
b0 1
b1100000000 2
03
17
#55000
b1011 &
#60000
b1000000000 "
b1100 &
b1000000000 (
b0 +
b1000000000 -
b10000000 0
b1000000000 2
03
05
07
#60200
b11111111000000000000000000000000000000000000000000000000000000000000000000000000000000000000000000000000000000000000000000000000 +
b11111111000000000000000000000000000000000000000000000000000000000000000000000000000000000000000000000000000000000000000000000000 ,
b0 -
1.
b0 0
b0 2
13
b11111111000000000000000000000000000000000000000000000000000000000000000000000000000000000000000000000000000000000000000000000000 4
#60300
b0 +
b1000000000 -
0.
b10000000 0
b1000000000 2
03
#60500
b0 1
b1000000000 2
03
17
#65000
b1101 &
#70000
b1110 &
#75000
b1111 &
#80000
b10000 &
#85000
b10001 &
#90000
b10010 &
#95000
b10011 &
